flask_cent.py
Flask_Cent-0.1.0.dist-info/DESCRIPTION.rst
Flask_Cent-0.1.0.dist-info/METADATA
Flask_Cent-0.1.0.dist-info/RECORD
Flask_Cent-0.1.0.dist-info/WHEEL
Flask_Cent-0.1.0.dist-info/metadata.json
Flask_Cent-0.1.0.dist-info/top_level.txt
