Metadata-Version: 2.0
Name: Flask-Cent
Version: 0.1.0
Summary: centrifugal/cent client for flask
Home-page: https://github.com/breakbase/flask-cent
Author: BreakBase.com
Author-email: oss@breakbase.com
License: MIT
Keywords: flask cent centrifugo
Platform: any
Classifier: Environment :: Web Environment
Classifier: Intended Audience :: Developers
Classifier: License :: OSI Approved :: MIT License
Classifier: Operating System :: OS Independent
Classifier: Programming Language :: Python
Classifier: Topic :: Internet :: WWW/HTTP :: Dynamic Content
Classifier: Topic :: Software Development :: Libraries :: Python Modules
Requires-Dist: Flask
Requires-Dist: blinker
Requires-Dist: cent
